odoo9_addon_product_multi_link-9.0.1.0.0-py2.7-nspkg.pth
odoo_addons/product_multi_link/__openerp__.py
odoo_addons/product_multi_link/__init__.py
odoo_addons/product_multi_link/README.rst
odoo_addons/product_multi_link/security/ir.model.access.csv
odoo_addons/product_multi_link/models/product.py
odoo_addons/product_multi_link/models/__init__.py
odoo_addons/product_multi_link/views/product_view.xml
odoo_addons/product_multi_link/static/description/icon.png
odoo9_addon_product_multi_link-9.0.1.0.0.dist-info/top_level.txt
odoo9_addon_product_multi_link-9.0.1.0.0.dist-info/WHEEL
odoo9_addon_product_multi_link-9.0.1.0.0.dist-info/RECORD
odoo9_addon_product_multi_link-9.0.1.0.0.dist-info/metadata.json
odoo9_addon_product_multi_link-9.0.1.0.0.dist-info/DESCRIPTION.rst
odoo9_addon_product_multi_link-9.0.1.0.0.dist-info/METADATA
odoo9_addon_product_multi_link-9.0.1.0.0.dist-info/namespace_packages.txt
